eval.py
image_eval/__init__.py
image_eval/encoders.py
image_eval/evaluators.py
image_eval/improved_aesthetic_predictor.py
image_eval/local_ab_test.py
image_eval/model_utils.py
image_eval/pairwise_evaluators.py
image_eval-0.1.8.dist-info/LICENSE
image_eval-0.1.8.dist-info/METADATA
image_eval-0.1.8.dist-info/WHEEL
image_eval-0.1.8.dist-info/entry_points.txt
image_eval-0.1.8.dist-info/top_level.txt
image_eval-0.1.8.dist-info/RECORD
