Metadata-Version: 2.1
Name: image-eval
Version: 0.1.8
Summary: A library for evaluating image generation models
Author: Storia AI
Author-email: founders@storia.ai
License: MIT License
License-File: LICENSE
Requires-Dist: image-reward ==1.5
Requires-Dist: insightface ==0.7.3
Requires-Dist: lpips ==0.1.4
Requires-Dist: networkx ==3.1
Requires-Dist: numpy
Requires-Dist: onnxruntime ==1.16.3
Requires-Dist: openai-clip ==1.0.1
Requires-Dist: piq ==0.8.0
Requires-Dist: pytorch-lightning ==2.0.8
Requires-Dist: requests ==2.31.0
Requires-Dist: scikit-learn ==1.3.2
Requires-Dist: streamlit ==1.26.0
Requires-Dist: sympy ==1.12
Requires-Dist: tabulate ==0.9.0
Requires-Dist: torch-fidelity ==0.3.0
Requires-Dist: transformers ==4.40.1
Requires-Dist: vendi-score ==0.0.3
